pyjou/__init__.py
pyjou/functions.py
pyjou/pyjou.py
pyjou/test.py
pyjou-0.0.12.dist-info/LICENSE
pyjou-0.0.12.dist-info/METADATA
pyjou-0.0.12.dist-info/WHEEL
pyjou-0.0.12.dist-info/top_level.txt
pyjou-0.0.12.dist-info/RECORD
