Metadata-Version: 2.1
Name: pyjou
Version: 0.0.12
Summary: Fluent Journal API
Home-page: https://github.com/nickuzmenkovorg/pyjou
Author: Nick Kuzmenkov
Author-email: nickuzmenkov@yahoo.com
License: UNKNOWN
Platform: UNKNOWN
Classifier: Programming Language :: Python :: 3.7
Classifier: License :: OSI Approved :: GNU General Public License v3 (GPLv3)
Requires-Dist: ipython (>=6)
Requires-Dist: nbformat (>=4)
Requires-Dist: nbconvert (>=5)
Requires-Dist: requests (>=2)
